denemesonuc/__init__.py
denemesonuc/fetchers/karnemiz.py
denemesonuc/fetchers/okulizyon.py
denemesonuc/models.py
denemesonuc/utils.py
denemesonuc-0.2.1.dist-info/LICENSE
denemesonuc-0.2.1.dist-info/METADATA
denemesonuc-0.2.1.dist-info/WHEEL
denemesonuc-0.2.1.dist-info/RECORD
